main.py
golden_rule-0.1.0.dist-info/METADATA
golden_rule-0.1.0.dist-info/WHEEL
golden_rule-0.1.0.dist-info/top_level.txt
golden_rule-0.1.0.dist-info/RECORD
