Metadata-Version: 2.4
Name: golden-rule
Version: 0.1.0
Summary: Add your description here
Requires-Python: >=3.12
Requires-Dist: torch>=2.8.0
Requires-Dist: torchvision>=0.23.0
